nopdf/__init__.py
nopdf/ocr.py
nopdf/scrape.py
nopdf_nuuuwan-1.0.0.dist-info/LICENCE
nopdf_nuuuwan-1.0.0.dist-info/METADATA
nopdf_nuuuwan-1.0.0.dist-info/WHEEL
nopdf_nuuuwan-1.0.0.dist-info/top_level.txt
nopdf_nuuuwan-1.0.0.dist-info/RECORD
