Metadata-Version: 2.1
Name: nopdf-nuuuwan
Version: 1.0.0
Summary: UNKNOWN
Home-page: https://github.com/nuuuwan/nopdf
Author: Nuwan I. Senaratna
Author-email: nuuuwan@gmail.com
License: UNKNOWN
Project-URL: Bug Tracker, https://github.com/nuuuwan/nopdf/issues
Platform: UNKNOWN
Classifier: Programming Language :: Python :: 3
Classifier: License :: OSI Approved :: MIT License
Classifier: Operating System :: OS Independent
Requires-Python: >=3.6
License-File: LICENCE
Requires-Dist: bs4
Requires-Dist: tweepy
Requires-Dist: Pillow
Requires-Dist: tesseract
Requires-Dist: tesseract-ocr
Requires-Dist: pytesseract
Requires-Dist: utils-nuuuwan
Requires-Dist: gig-nuuuwan
